supercap/__init__.py
supercap/supercapacitormodel.py
supercap-0.3.1.dist-info/LICENSE.txt
supercap-0.3.1.dist-info/METADATA
supercap-0.3.1.dist-info/WHEEL
supercap-0.3.1.dist-info/top_level.txt
supercap-0.3.1.dist-info/RECORD
