Metadata-Version: 2.1
Name: supercap
Version: 0.3.1
Summary: Supercapacitor Modelling package for Python
Home-page: https://github.com/venkat0249/SuperCap-Python
Author: Daniel Lavin and Venkatesh Pampana
Author-email: venkatmr.perfect@gmail.com
License: MIT
Keywords: supercapacitor,energy,simulation,modelling,model
Platform: UNKNOWN
Classifier: Development Status :: 4 - Beta
Classifier: Intended Audience :: Science/Research
Classifier: Topic :: Scientific/Engineering
Classifier: License :: OSI Approved :: MIT License
Classifier: Programming Language :: Python :: 3
Classifier: Programming Language :: Python :: 3.4
Classifier: Programming Language :: Python :: 3.5
Classifier: Programming Language :: Python :: 3.6
Requires-Dist: pandas
Requires-Dist: numpy
Requires-Dist: prompt-toolkit
